ray_mcp/__init__.py
ray_mcp/main.py
ray_mcp/ray_manager.py
ray_mcp/tools.py
ray_mcp/types.py
ray_mcp/worker_manager.py
ray_mcp_server-0.2.0.dist-info/METADATA
ray_mcp_server-0.2.0.dist-info/WHEEL
ray_mcp_server-0.2.0.dist-info/entry_points.txt
ray_mcp_server-0.2.0.dist-info/licenses/LICENSE
ray_mcp_server-0.2.0.dist-info/licenses/NOTICE
ray_mcp_server-0.2.0.dist-info/RECORD
