Metadata-Version: 2.4
Name: ray-mcp-server
Version: 0.2.0
Summary: ⚡ Claude Desktop MCP server for Ray distributed computing - manage clusters through natural language!
Project-URL: Homepage, https://github.com/pradeepiyer/ray-mcp
Project-URL: Documentation, https://github.com/pradeepiyer/ray-mcp#readme
Project-URL: Repository, https://github.com/pradeepiyer/ray-mcp.git
Project-URL: Issues, https://github.com/pradeepiyer/ray-mcp/issues
Author-email: Vaskin Kissoyan <vaskin@gmail.com>
Maintainer-email: Vaskin Kissoyan <vaskin@gmail.com>
License: Apache-2.0
License-File: LICENSE
License-File: NOTICE
Keywords: ai,claude-desktop,distributed-computing,machine-learning,mcp,ray
Classifier: Development Status :: 4 - Beta
Classifier: Intended Audience :: Developers
Classifier: License :: OSI Approved :: Apache Software License
Classifier: Operating System :: OS Independent
Classifier: Programming Language :: Python :: 3
Classifier: Programming Language :: Python :: 3.12
Classifier: Topic :: Scientific/Engineering :: Artificial Intelligence
Classifier: Topic :: System :: Distributed Computing
Requires-Python: >=3.12
Requires-Dist: click>=8.0.0
Requires-Dist: mcp>=1.0.0
Requires-Dist: psutil>=5.9.0
Requires-Dist: pydantic>=2.0.0
Requires-Dist: ray[default]==2.47.0
Requires-Dist: requests>=2.28.0
Requires-Dist: rich>=13.0.0
Requires-Dist: tqdm>=4.64.0
Requires-Dist: typing-extensions>=4.5.0
Provides-Extra: examples
